superbio/__init__.py
superbio/auth.py
superbio/client.py
superbio/consts.py
superbio/endpoints.py
superbio/exceptions.py
superbio/utils.py
tests/__init__.py
tests/conftest.py
tests/test_auth.py
tests/test_client.py
tests/test_utils.py
tests/test_files/deg_background_preprocessed.csv
tests/test_files/deg_experimental_preprocessed.csv
superbio-0.1.7.dist-info/METADATA
superbio-0.1.7.dist-info/WHEEL
superbio-0.1.7.dist-info/top_level.txt
superbio-0.1.7.dist-info/RECORD
